mangadex_openapi/__init__.py
mangadex_openapi/api_client.py
mangadex_openapi/configuration.py
mangadex_openapi/rest.py
mangadex_openapi/api/__init__.py
mangadex_openapi/api/account_api.py
mangadex_openapi/api/at_home_api.py
mangadex_openapi/api/auth_api.py
mangadex_openapi/api/author_api.py
mangadex_openapi/api/captcha_api.py
mangadex_openapi/api/chapter_api.py
mangadex_openapi/api/custom_list_api.py
mangadex_openapi/api/feed_api.py
mangadex_openapi/api/infrastructure_api.py
mangadex_openapi/api/legacy_api.py
mangadex_openapi/api/manga_api.py
mangadex_openapi/api/scanlation_group_api.py
mangadex_openapi/api/search_api.py
mangadex_openapi/api/user_api.py
mangadex_openapi/models/__init__.py
mangadex_openapi/models/account_activate_response.py
mangadex_openapi/models/author.py
mangadex_openapi/models/author_attributes.py
mangadex_openapi/models/author_create.py
mangadex_openapi/models/author_edit.py
mangadex_openapi/models/author_list.py
mangadex_openapi/models/author_response.py
mangadex_openapi/models/body.py
mangadex_openapi/models/chapter.py
mangadex_openapi/models/chapter_attributes.py
mangadex_openapi/models/chapter_edit.py
mangadex_openapi/models/chapter_list.py
mangadex_openapi/models/chapter_request.py
mangadex_openapi/models/chapter_response.py
mangadex_openapi/models/check_response.py
mangadex_openapi/models/create_account.py
mangadex_openapi/models/create_scanlation_group.py
mangadex_openapi/models/custom_list.py
mangadex_openapi/models/custom_list_attributes.py
mangadex_openapi/models/custom_list_create.py
mangadex_openapi/models/custom_list_edit.py
mangadex_openapi/models/custom_list_list.py
mangadex_openapi/models/custom_list_response.py
mangadex_openapi/models/error.py
mangadex_openapi/models/error_response.py
mangadex_openapi/models/inline_response200.py
mangadex_openapi/models/inline_response2001.py
mangadex_openapi/models/inline_response2002.py
mangadex_openapi/models/inline_response2003.py
mangadex_openapi/models/inline_response2004.py
mangadex_openapi-0.4.1.dist-info/WHEEL
mangadex_openapi-0.4.1.dist-info/METADATA
mangadex_openapi-0.4.1.dist-info/RECORD
