Metadata-Version: 2.1
Name: mangadex_openapi
Version: 0.4.1
Summary: MangaDex API
Home-page: https://github.com/ongyx/mangadex_openapi
Author: Ong Yong Xin
Author-email: ongyongxin2020+github@gmail.com
Requires-Python: >=3.6
Classifier: Programming Language :: Python :: 3
Classifier: License :: OSI Approved :: MIT License
Classifier: Operating System :: OS Independent
Requires-Dist: certifi>=14.05.14
Requires-Dist: six>=1.10
Requires-Dist: python-dateutil>=2.5.3
Requires-Dist: urllib3>=1.15.1
Requires-Dist: pydoc-markdown>=3.10.1 ; extra == "docs"
Requires-Dist: black>=21.5b1 ; extra == "docs"
Requires-Dist: pytest>=6.2.2 ; extra == "test"
Provides-Extra: docs
Provides-Extra: test
